vang/artifactory/__init__.py
vang/artifactory/api.py
vang/artifactory/delete.py
vang/artifactory/diff_repos.py
vang/artifactory/download_repo_content.py
vang/artifactory/list_repo_content.py
vang/artifactory/list_repos.py
vang/artifactory/mirror.py
vang/artifactory/mirror_config.py
vang/artifactory/publish.py
vang/artifactory/utils.py
vang/azdo/__init__.py
vang/azdo/clone_repos.py
vang/azdo/create_build_definition.py
vang/azdo/create_repo.py
vang/azdo/get_project.py
vang/azdo/list_builds.py
vang/azdo/list_projects.py
vang/azdo/list_repos.py
vang/azdo/queue_build.py
vang/bitbucket/__init__.py
vang/bitbucket/api.py
vang/bitbucket/clone_repos.py
vang/bitbucket/clone_repos_with_commits_since.py
vang/bitbucket/create_from_template.py
vang/bitbucket/create_repo.py
vang/bitbucket/delete_repos.py
vang/bitbucket/enable_webhooks.py
vang/bitbucket/fork_repos.py
vang/bitbucket/fork_repos_git.py
vang/bitbucket/get_branches.py
vang/bitbucket/get_clone_urls.py
vang/bitbucket/get_clone_urls_grep.py
vang/bitbucket/get_commits.py
vang/bitbucket/get_default_branches.py
vang/bitbucket/get_projects.py
vang/bitbucket/get_repos.py
vang/bitbucket/get_tags.py
vang/bitbucket/has_branch.py
vang/bitbucket/has_tag.py
vang/bitbucket/open_remote.py
vang/bitbucket/set_default_branches.py
vang/bitbucket/set_webhooks.py
vang/bitbucket/utils.py
vang/bitbucket/validate_projects.py
vang/core/__init__.py
vang/core/core.py
vang/git/__init__.py
vang/git/filter_branch.py
vang/git/open_remote.py
vang/git/patch_tag.py
vang/git/patchish_refs.py
vang/github/__init__.py
vang/github/example.py
vang/jenkins/__init__.py
vang/jenkins/api.py
vang/jenkins/copy_job.py
vang/jenkins/copy_jobs.py
vang/jenkins/copy_jobs_example.py
vang/jenkins/delete_jobs.py
vang/jenkins/download_configs.py
vang/jenkins/get_jobs.py
vang/jenkins/trigger_builds.py
vang/jenkins/upload_configs.py
vang/jenkins/view.py
vang/maven/__init__.py
vang/maven/get_artifact_id.py
vang/maven/get_dependants.py
vang/maven/get_dependencies.py
vang-1.3.1.dist-info/LICENSE
vang-1.3.1.dist-info/METADATA
vang-1.3.1.dist-info/WHEEL
vang-1.3.1.dist-info/top_level.txt
vang-1.3.1.dist-info/RECORD
