Metadata-Version: 2.1
Name: vang
Version: 1.3.1
Summary: Scripts
Home-page: https://github.com/bjuvensjo/scripts
Author: Magnus Bjuvensjö
Author-email: bjuvensjo@gmail.com
License: MIT
Keywords: python script artifactory azdo bitbucket git github jenkins maven nexus3 tfs
Platform: UNKNOWN
Classifier: Development Status :: 4 - Beta
Classifier: Topic :: Utilities
Classifier: License :: OSI Approved :: MIT License
License-File: LICENSE
Requires-Dist: more-itertools
Requires-Dist: requests
Requires-Dist: pytest
